semanticpy/__init__.py
semanticpy/errors.py
semanticpy/logging.py
semanticpy/version.txt
semanticpy/profiles/linked-art.json
semanticpy/types/__init__.py
semanticpy/types/attributed.py
semanticpy/types/dictionary.py
semanticpy/types/namespace.py
semanticpy/types/node.py
semanticpy-1.2.1.dist-info/licenses/LICENSE.md
semanticpy-1.2.1.dist-info/METADATA
semanticpy-1.2.1.dist-info/WHEEL
semanticpy-1.2.1.dist-info/top_level.txt
semanticpy-1.2.1.dist-info/zip-safe
semanticpy-1.2.1.dist-info/RECORD
