Metadata-Version: 2.4
Name: semanticpy
Version: 1.2.1
Summary: Simplifies the creation of linked data documents using Python classes and properties.
Author: Daniel Sissman
License-Expression: MIT
Project-URL: documentation, https://github.com/bluebinary/semanticpy/blob/main/README.md
Project-URL: changelog, https://github.com/bluebinary/semanticpy/blob/main/CHANGELOG.md
Project-URL: repository, https://github.com/bluebinary/semanticpy
Project-URL: issues, https://github.com/bluebinary/semanticpy/issues
Project-URL: homepage, https://github.com/bluebinary/semanticpy
Keywords: semantic,linked data,LOD,JSON-LD,RDF
Classifier: Programming Language :: Python :: 3
Classifier: Programming Language :: Python :: 3.10
Classifier: Programming Language :: Python :: 3.11
Classifier: Programming Language :: Python :: 3.12
Classifier: Programming Language :: Python :: 3.13
Requires-Python: >=3.10
License-File: LICENSE.md
Requires-Dist: requests
Provides-Extra: development
Requires-Dist: black==24.3.0; extra == "development"
Requires-Dist: pytest==7.2.1; extra == "development"
Provides-Extra: distribution
Requires-Dist: build; extra == "distribution"
Requires-Dist: twine; extra == "distribution"
Requires-Dist: wheel; extra == "distribution"
Dynamic: license-file
